capreolus/__init__.py
capreolus/evaluator.py
capreolus/run.py
capreolus/benchmark/__init__.py
capreolus/benchmark/antique.py
capreolus/benchmark/codesearchnet.py
capreolus/benchmark/covid.py
capreolus/benchmark/dummy.py
capreolus/benchmark/msmarco.py
capreolus/benchmark/nf.py
capreolus/benchmark/robust04.py
capreolus/collection/__init__.py
capreolus/collection/antique.py
capreolus/collection/codesearchnet.py
capreolus/collection/covid.py
capreolus/collection/dummy.py
capreolus/collection/msmarco.py
capreolus/collection/nf.py
capreolus/collection/robust04.py
capreolus/data/antique.json
capreolus/data/dummy.yaml
capreolus/data/dummy_folds.json
capreolus/data/msmarcopassage.folds.json
capreolus/data/qrels.antique.txt
capreolus/data/qrels.antique_test.txt
capreolus/data/qrels.dummy.txt
capreolus/data/qrels.msmarcopassage.txt
capreolus/data/qrels.robust2004.txt
capreolus/data/rob04_cedr_folds.json
capreolus/data/rob04_yang19_folds.json
capreolus/data/rob04_yang19_rm3.run
capreolus/data/robust04.yaml
capreolus/data/topics.antique.txt
capreolus/data/topics.dummy.txt
capreolus/data/topics.robust04.301-450.601-700.txt
capreolus/data/dummy/data/dummy_trec_doc
capreolus/extractor/__init__.py
capreolus/extractor/bagofwords.py
capreolus/extractor/bertpassage.py
capreolus/extractor/berttext.py
capreolus/extractor/common.py
capreolus/extractor/deeptileextractor.py
capreolus/extractor/embedtext.py
capreolus/extractor/pooled_bertpassage.py
capreolus/extractor/slowembedtext.py
capreolus/index/__init__.py
capreolus/index/anserini.py
capreolus/index/tests/__init__.py
capreolus/index/tests/test_index.py
capreolus/reranker/CDSSM.py
capreolus/reranker/CEDRKNRM.py
capreolus/reranker/ConvKNRM.py
capreolus/reranker/DRMM.py
capreolus/reranker/DRMMTKS.py
capreolus/reranker/DSSM.py
capreolus/reranker/DUET.py
capreolus/reranker/DeepTileBar.py
capreolus/reranker/HINT.py
capreolus/reranker/KNRM.py
capreolus/reranker/PACRR.py
capreolus/reranker/POSITDRMM.py
capreolus/reranker/TFBERTMaxP.py
capreolus-0.2.6.dist-info/LICENSE
capreolus-0.2.6.dist-info/METADATA
capreolus-0.2.6.dist-info/WHEEL
capreolus-0.2.6.dist-info/top_level.txt
capreolus-0.2.6.dist-info/RECORD
