Metadata-Version: 2.1
Name: capreolus
Version: 0.2.6
Summary: A toolkit for end-to-end neural ad hoc retrieval
Home-page: https://capreolus.ai
Author: Andrew Yates
Author-email: initial-then-last@mpi-inf.mpg.de
License: UNKNOWN
Platform: UNKNOWN
Classifier: Programming Language :: Python :: 3
Classifier: Operating System :: OS Independent
Requires-Python: >=3.6
Requires-Dist: torch (==1.6)
Requires-Dist: torchvision (==0.7)
Requires-Dist: cython
Requires-Dist: pre-commit
Requires-Dist: profane (>=0.2.0)
Requires-Dist: SQLAlchemy
Requires-Dist: sqlalchemy-utils
Requires-Dist: psycopg2-binary
Requires-Dist: matplotlib
Requires-Dist: colorlog (==4.0.2)
Requires-Dist: pytrec-eval (>=0.5)
Requires-Dist: pytest
Requires-Dist: pyjnius (==1.2.1)
Requires-Dist: pymagnitude (==0.1.143)
Requires-Dist: h5py (==2.10.0)
Requires-Dist: nltk (==3.4.5)
Requires-Dist: pytest-mock
Requires-Dist: mock
Requires-Dist: pyserini (==0.9.3.0)
Requires-Dist: numpy
Requires-Dist: scipy
Requires-Dist: google-api-python-client
Requires-Dist: oauth2client
Requires-Dist: tensorflow (<2.5,>=2.4)
Requires-Dist: transformers (==3.1.0)
Requires-Dist: tensorflow-ranking
Requires-Dist: Pillow
Requires-Dist: beautifulsoup4
Requires-Dist: lxml
Requires-Dist: scispacy
Requires-Dist: smart-open
Requires-Dist: spacy (<3.0)
Requires-Dist: pandas
